capmonster_python/__init__.py
capmonster_python/client.py
capmonster_python/exceptions.py
capmonster_python/methods.py
capmonster_python/tasks/__init__.py
capmonster_python/tasks/basilisk.py
capmonster_python/tasks/binance.py
capmonster_python/tasks/complex_image_recaptcha.py
capmonster_python/tasks/complex_image_recognition.py
capmonster_python/tasks/datadome.py
capmonster_python/tasks/geetest.py
capmonster_python/tasks/image_to_text.py
capmonster_python/tasks/imperva.py
capmonster_python/tasks/prosopo.py
capmonster_python/tasks/recaptcha_v2.py
capmonster_python/tasks/recaptcha_v2_enterprise.py
capmonster_python/tasks/recaptcha_v3.py
capmonster_python/tasks/task.py
capmonster_python/tasks/temu.py
capmonster_python/tasks/tendi.py
capmonster_python/tasks/turnstile.py
capmonster_python-4.0.0.dist-info/licenses/LICENSE
capmonster_python-4.0.0.dist-info/METADATA
capmonster_python-4.0.0.dist-info/WHEEL
capmonster_python-4.0.0.dist-info/top_level.txt
capmonster_python-4.0.0.dist-info/RECORD
