Metadata-Version: 2.4
Name: capmonster_python
Version: 4.0.0
Summary: capmonster.cloud library/package for Python
Author-email: Alperen Sert <business@alperen.io>
License: MIT
Project-URL: Documentation, https://alperensert.github.io/capmonster_python/
Project-URL: Source, https://github.com/alperensert/capmonster_python/
Project-URL: Tracker, https://github.com/alperensert/capmonster_python/issues
Classifier: Development Status :: 4 - Beta
Classifier: License :: OSI Approved :: MIT License
Classifier: Programming Language :: Python :: 3
Classifier: Programming Language :: Python :: 3.9
Classifier: Programming Language :: Python :: 3.10
Classifier: Programming Language :: Python :: 3.11
Requires-Python: >=3.9
License-File: LICENSE
Requires-Dist: httpx>=0.27.0
Requires-Dist: pydantic>=2.0
Dynamic: license-file
